{"data":[{"type":"heatmap","colorbar":{"title":{"side":"right","text":"← KUBO faster | HTTP faster →"}},"colorscale":"Viridis","name":"name","reversescale":true,"x":["ap-southeast-2","eu-central-1","us-east-2","us-west-1"],"y":[30,40,50,60,70,80,90],"yaxis":"","z":[[2.317321178120617,3.3956043956043955,0.7265275707898659,0.31058234189104567],[2.314012956017729,3.551948051948052,0.7209136331192006,0.3144768856447689],[2.0472103004291844,3.978915662650602,0.667300380228137,0.326397146254459],[2.0322093608454956,5.167597765363128,0.6724550898203592,0.3354357798165138],[1.7334458034584561,4.837837837837838,0.6900780379041248,0.34721471065440773],[1.169696128763702,3.5378421900161032,0.4996501049685095,0.1312910284463895],[1.054047561854432,1.0055213421108515,0.343970440040309,0.17432698621142484]]}],"layout":{"annotations":[{"xref":"x1","yref":"y1","x":"ap-southeast-2","y":30,"text":"2.317","font":{"color":"#EEEEEE"},"showarrow":false},{"xref":"x1","yref":"y1","x":"eu-central-1","y":30,"text":"3.396","font":{"color":"#EEEEEE"},"showarrow":false},{"xref":"x1","yref":"y1","x":"us-east-2","y":30,"text":"0.727","font":{"color":""},"showarrow":false},{"xref":"x1","yref":"y1","x":"us-west-1","y":30,"text":"0.311","font":{"color":""},"showarrow":false},{"xref":"x1","yref":"y1","x":"ap-southeast-2","y":40,"text":"2.314","font":{"color":"#EEEEEE"},"showarrow":false},{"xref":"x1","yref":"y1","x":"eu-central-1","y":40,"text":"3.552","font":{"color":"#EEEEEE"},"showarrow":false},{"xref":"x1","yref":"y1","x":"us-east-2","y":40,"text":"0.721","font":{"color":""},"showarrow":false},{"xref":"x1","yref":"y1","x":"us-west-1","y":40,"text":"0.314","font":{"color":""},"showarrow":false},{"xref":"x1","yref":"y1","x":"ap-southeast-2","y":50,"text":"2.047","font":{"color":"#EEEEEE"},"showarrow":false},{"xref":"x1","yref":"y1","x":"eu-central-1","y":50,"text":"3.979","font":{"color":"#EEEEEE"},"showarrow":false},{"xref":"x1","yref":"y1","x":"us-east-2","y":50,"text":"0.667","font":{"color":""},"showarrow":false},{"xref":"x1","yref":"y1","x":"us-west-1","y":50,"text":"0.326","font":{"color":""},"showarrow":false},{"xref":"x1","yref":"y1","x":"ap-southeast-2","y":60,"text":"2.032","font":{"color":"#EEEEEE"},"showarrow":false},{"xref":"x1","yref":"y1","x":"eu-central-1","y":60,"text":"5.168","font":{"color":"#EEEEEE"},"showarrow":false},{"xref":"x1","yref":"y1","x":"us-east-2","y":60,"text":"0.672","font":{"color":""},"showarrow":false},{"xref":"x1","yref":"y1","x":"us-west-1","y":60,"text":"0.335","font":{"color":""},"showarrow":false},{"xref":"x1","yref":"y1","x":"ap-southeast-2","y":70,"text":"1.733","font":{"color":"#EEEEEE"},"showarrow":false},{"xref":"x1","yref":"y1","x":"eu-central-1","y":70,"text":"4.838","font":{"color":"#EEEEEE"},"showarrow":false},{"xref":"x1","yref":"y1","x":"us-east-2","y":70,"text":"0.690","font":{"color":""},"showarrow":false},{"xref":"x1","yref":"y1","x":"us-west-1","y":70,"text":"0.347","font":{"color":""},"showarrow":false},{"xref":"x1","yref":"y1","x":"ap-southeast-2","y":80,"text":"1.170","font":{"color":""},"showarrow":false},{"xref":"x1","yref":"y1","x":"eu-central-1","y":80,"text":"3.538","font":{"color":"#EEEEEE"},"showarrow":false},{"xref":"x1","yref":"y1","x":"us-east-2","y":80,"text":"0.500","font":{"color":""},"showarrow":false},{"xref":"x1","yref":"y1","x":"us-west-1","y":80,"text":"0.131","font":{"color":""},"showarrow":false},{"xref":"x1","yref":"y1","x":"ap-southeast-2","y":90,"text":"1.054","font":{"color":""},"showarrow":false},{"xref":"x1","yref":"y1","x":"eu-central-1","y":90,"text":"1.006","font":{"color":""},"showarrow":false},{"xref":"x1","yref":"y1","x":"us-east-2","y":90,"text":"0.344","font":{"color":""},"showarrow":false},{"xref":"x1","yref":"y1","x":"us-west-1","y":90,"text":"0.174","font":{"color":""},"showarrow":false}],"dragmode":false,"margin":{"b":30},"title":{"font":{"size":10},"text":"Data: 21 Dec 2024 - 28 Dec 2024 (ttfb, blog.ipfs.tech). Source: Tiros.","x":1,"xanchor":"right","y":0.01,"yanchor":"bottom"},"xaxis":{"automargin":true,"side":"top","title":{"text":"AWS Region"}},"yaxis":{"automargin":true,"title":{"text":"Percentile"}}},"params":null,"dynamicLayout":null,"config":null}
