{"data":[{"type":"heatmap","colorbar":{"title":{"side":"right","text":"← Kubo faster | HTTP faster →"}},"colorscale":"Viridis","name":"name","reversescale":true,"x":["af-south-1","ap-south-1","ap-southeast-2","eu-central-1","sa-east-1","us-east-2","us-west-1"],"y":[30,40,50,60,70,80,90],"yaxis":"","z":[[3.027670171555064,1.800747198007472,1.9432703003337042,2.826330532212885,1.786115569823435,0.8915254237288137,0.6645821489482661],[3.0507478632478633,1.7560975609756095,1.985003657644477,2.8533653846153846,1.8392996108949415,1.0065207265952492,0.8153503893214684],[3.437978560490046,1.7150118603863098,2.0790328401299165,2.70703125,1.9249056603773584,1.039347007115948,0.9567333693888588],[3.2959662288930582,1.4055961683892109,2.1457375309515387,2.2373113854595332,2.0300429184549356,1.1072638313887844,1.0637429882712903],[3.1574539363484084,1.4101425566721197,2.2025101763907733,1.738377392889699,2.039706373039706,0.6468408375023162,1.179582366589327],[2.654617253948967,1.0155394405801392,2.1936576354679804,1.5136031851360319,1.9306324686680267,0.6916193426260541,1.3045833333333334],[1.4731847591660674,0.9790314528207688,2.0664784394250515,0.5730027548209367,1.0234113712374582,0.6653867251782777,0.6434142114384749]]}],"layout":{"annotations":[{"xref":"x1","yref":"y1","x":"af-south-1","y":30,"text":"3.028","font":{"color":"#EEEEEE"},"showarrow":false},{"xref":"x1","yref":"y1","x":"ap-south-1","y":30,"text":"1.801","font":{"color":"#EEEEEE"},"showarrow":false},{"xref":"x1","yref":"y1","x":"ap-southeast-2","y":30,"text":"1.943","font":{"color":"#EEEEEE"},"showarrow":false},{"xref":"x1","yref":"y1","x":"eu-central-1","y":30,"text":"2.826","font":{"color":"#EEEEEE"},"showarrow":false},{"xref":"x1","yref":"y1","x":"sa-east-1","y":30,"text":"1.786","font":{"color":"#EEEEEE"},"showarrow":false},{"xref":"x1","yref":"y1","x":"us-east-2","y":30,"text":"0.892","font":{"color":"#EEEEEE"},"showarrow":false},{"xref":"x1","yref":"y1","x":"us-west-1","y":30,"text":"0.665","font":{"color":""},"showarrow":false},{"xref":"x1","yref":"y1","x":"af-south-1","y":40,"text":"3.051","font":{"color":"#EEEEEE"},"showarrow":false},{"xref":"x1","yref":"y1","x":"ap-south-1","y":40,"text":"1.756","font":{"color":"#EEEEEE"},"showarrow":false},{"xref":"x1","yref":"y1","x":"ap-southeast-2","y":40,"text":"1.985","font":{"color":"#EEEEEE"},"showarrow":false},{"xref":"x1","yref":"y1","x":"eu-central-1","y":40,"text":"2.853","font":{"color":"#EEEEEE"},"showarrow":false},{"xref":"x1","yref":"y1","x":"sa-east-1","y":40,"text":"1.839","font":{"color":"#EEEEEE"},"showarrow":false},{"xref":"x1","yref":"y1","x":"us-east-2","y":40,"text":"1.007","font":{"color":"#EEEEEE"},"showarrow":false},{"xref":"x1","yref":"y1","x":"us-west-1","y":40,"text":"0.815","font":{"color":"#EEEEEE"},"showarrow":false},{"xref":"x1","yref":"y1","x":"af-south-1","y":50,"text":"3.438","font":{"color":"#EEEEEE"},"showarrow":false},{"xref":"x1","yref":"y1","x":"ap-south-1","y":50,"text":"1.715","font":{"color":"#EEEEEE"},"showarrow":false},{"xref":"x1","yref":"y1","x":"ap-southeast-2","y":50,"text":"2.079","font":{"color":"#EEEEEE"},"showarrow":false},{"xref":"x1","yref":"y1","x":"eu-central-1","y":50,"text":"2.707","font":{"color":"#EEEEEE"},"showarrow":false},{"xref":"x1","yref":"y1","x":"sa-east-1","y":50,"text":"1.925","font":{"color":"#EEEEEE"},"showarrow":false},{"xref":"x1","yref":"y1","x":"us-east-2","y":50,"text":"1.039","font":{"color":"#EEEEEE"},"showarrow":false},{"xref":"x1","yref":"y1","x":"us-west-1","y":50,"text":"0.957","font":{"color":"#EEEEEE"},"showarrow":false},{"xref":"x1","yref":"y1","x":"af-south-1","y":60,"text":"3.296","font":{"color":"#EEEEEE"},"showarrow":false},{"xref":"x1","yref":"y1","x":"ap-south-1","y":60,"text":"1.406","font":{"color":"#EEEEEE"},"showarrow":false},{"xref":"x1","yref":"y1","x":"ap-southeast-2","y":60,"text":"2.146","font":{"color":"#EEEEEE"},"showarrow":false},{"xref":"x1","yref":"y1","x":"eu-central-1","y":60,"text":"2.237","font":{"color":"#EEEEEE"},"showarrow":false},{"xref":"x1","yref":"y1","x":"sa-east-1","y":60,"text":"2.030","font":{"color":"#EEEEEE"},"showarrow":false},{"xref":"x1","yref":"y1","x":"us-east-2","y":60,"text":"1.107","font":{"color":"#EEEEEE"},"showarrow":false},{"xref":"x1","yref":"y1","x":"us-west-1","y":60,"text":"1.064","font":{"color":"#EEEEEE"},"showarrow":false},{"xref":"x1","yref":"y1","x":"af-south-1","y":70,"text":"3.157","font":{"color":"#EEEEEE"},"showarrow":false},{"xref":"x1","yref":"y1","x":"ap-south-1","y":70,"text":"1.410","font":{"color":"#EEEEEE"},"showarrow":false},{"xref":"x1","yref":"y1","x":"ap-southeast-2","y":70,"text":"2.203","font":{"color":"#EEEEEE"},"showarrow":false},{"xref":"x1","yref":"y1","x":"eu-central-1","y":70,"text":"1.738","font":{"color":"#EEEEEE"},"showarrow":false},{"xref":"x1","yref":"y1","x":"sa-east-1","y":70,"text":"2.040","font":{"color":"#EEEEEE"},"showarrow":false},{"xref":"x1","yref":"y1","x":"us-east-2","y":70,"text":"0.647","font":{"color":""},"showarrow":false},{"xref":"x1","yref":"y1","x":"us-west-1","y":70,"text":"1.180","font":{"color":"#EEEEEE"},"showarrow":false},{"xref":"x1","yref":"y1","x":"af-south-1","y":80,"text":"2.655","font":{"color":"#EEEEEE"},"showarrow":false},{"xref":"x1","yref":"y1","x":"ap-south-1","y":80,"text":"1.016","font":{"color":"#EEEEEE"},"showarrow":false},{"xref":"x1","yref":"y1","x":"ap-southeast-2","y":80,"text":"2.194","font":{"color":"#EEEEEE"},"showarrow":false},{"xref":"x1","yref":"y1","x":"eu-central-1","y":80,"text":"1.514","font":{"color":"#EEEEEE"},"showarrow":false},{"xref":"x1","yref":"y1","x":"sa-east-1","y":80,"text":"1.931","font":{"color":"#EEEEEE"},"showarrow":false},{"xref":"x1","yref":"y1","x":"us-east-2","y":80,"text":"0.692","font":{"color":""},"showarrow":false},{"xref":"x1","yref":"y1","x":"us-west-1","y":80,"text":"1.305","font":{"color":"#EEEEEE"},"showarrow":false},{"xref":"x1","yref":"y1","x":"af-south-1","y":90,"text":"1.473","font":{"color":"#EEEEEE"},"showarrow":false},{"xref":"x1","yref":"y1","x":"ap-south-1","y":90,"text":"0.979","font":{"color":"#EEEEEE"},"showarrow":false},{"xref":"x1","yref":"y1","x":"ap-southeast-2","y":90,"text":"2.066","font":{"color":"#EEEEEE"},"showarrow":false},{"xref":"x1","yref":"y1","x":"eu-central-1","y":90,"text":"0.573","font":{"color":""},"showarrow":false},{"xref":"x1","yref":"y1","x":"sa-east-1","y":90,"text":"1.023","font":{"color":"#EEEEEE"},"showarrow":false},{"xref":"x1","yref":"y1","x":"us-east-2","y":90,"text":"0.665","font":{"color":""},"showarrow":false},{"xref":"x1","yref":"y1","x":"us-west-1","y":90,"text":"0.643","font":{"color":""},"showarrow":false}],"dragmode":false,"margin":{"b":30},"title":{"font":{"size":10},"text":"Data: 15 Jul 2023 - 22 Jul 2023 (ttfb, consensuslab.world). Source: Tiros.","x":1,"xanchor":"right","y":0.01,"yanchor":"bottom"},"xaxis":{"automargin":true,"side":"top","title":{"text":"AWS Region"}},"yaxis":{"automargin":true,"title":{"text":"Percentile"}}},"params":null,"dynamicLayout":null,"config":null}
