{"data":[{"type":"heatmap","colorbar":{"title":{"side":"right","text":"Latency in s"}},"colorscale":"Viridis","name":"FCP","reversescale":true,"x":["ap-southeast-2","eu-central-1","us-east-2","us-west-1"],"y":["blog.ipfs.tech","blog.libp2p.io","docs.ipfs.tech","docs.libp2p.io","en.wikipedia-on-ipfs.org/wiki","ipfs.tech","ipld.io","probelab.io","specs.ipfs.tech","web3.storage"],"yaxis":"","z":[[1.39055,0.28295,0.30135,0.23925],[1.33125,0.2442,0.2737,0.2054],[1.31885,0.3019,0.3091,0.2631],[1.0772,0.2342,0.25675,0.2216],[6.6197,1.9942,3.3349,2.4971],[1.4279,0.30995,0.3277,0.2835],[1.15865,0.2338,0.26765,0.2158],[1.36165,0.2403,0.3083,0.2272],[0.9709,0.1759,0.1999,0.1471],[1.34825,0.27875,0.30275,0.23975]]}],"layout":{"annotations":[{"xref":"x1","yref":"y1","x":"ap-southeast-2","y":"blog.ipfs.tech","text":"1.391","font":{"color":""},"showarrow":false},{"xref":"x1","yref":"y1","x":"eu-central-1","y":"blog.ipfs.tech","text":"0.283","font":{"color":""},"showarrow":false},{"xref":"x1","yref":"y1","x":"us-east-2","y":"blog.ipfs.tech","text":"0.301","font":{"color":""},"showarrow":false},{"xref":"x1","yref":"y1","x":"us-west-1","y":"blog.ipfs.tech","text":"0.239","font":{"color":""},"showarrow":false},{"xref":"x1","yref":"y1","x":"ap-southeast-2","y":"blog.libp2p.io","text":"1.331","font":{"color":""},"showarrow":false},{"xref":"x1","yref":"y1","x":"eu-central-1","y":"blog.libp2p.io","text":"0.244","font":{"color":""},"showarrow":false},{"xref":"x1","yref":"y1","x":"us-east-2","y":"blog.libp2p.io","text":"0.274","font":{"color":""},"showarrow":false},{"xref":"x1","yref":"y1","x":"us-west-1","y":"blog.libp2p.io","text":"0.205","font":{"color":""},"showarrow":false},{"xref":"x1","yref":"y1","x":"ap-southeast-2","y":"docs.ipfs.tech","text":"1.319","font":{"color":""},"showarrow":false},{"xref":"x1","yref":"y1","x":"eu-central-1","y":"docs.ipfs.tech","text":"0.302","font":{"color":""},"showarrow":false},{"xref":"x1","yref":"y1","x":"us-east-2","y":"docs.ipfs.tech","text":"0.309","font":{"color":""},"showarrow":false},{"xref":"x1","yref":"y1","x":"us-west-1","y":"docs.ipfs.tech","text":"0.263","font":{"color":""},"showarrow":false},{"xref":"x1","yref":"y1","x":"ap-southeast-2","y":"docs.libp2p.io","text":"1.077","font":{"color":""},"showarrow":false},{"xref":"x1","yref":"y1","x":"eu-central-1","y":"docs.libp2p.io","text":"0.234","font":{"color":""},"showarrow":false},{"xref":"x1","yref":"y1","x":"us-east-2","y":"docs.libp2p.io","text":"0.257","font":{"color":""},"showarrow":false},{"xref":"x1","yref":"y1","x":"us-west-1","y":"docs.libp2p.io","text":"0.222","font":{"color":""},"showarrow":false},{"xref":"x1","yref":"y1","x":"ap-southeast-2","y":"en.wikipedia-on-ipfs.org/wiki","text":"6.620","font":{"color":"#EEEEEE"},"showarrow":false},{"xref":"x1","yref":"y1","x":"eu-central-1","y":"en.wikipedia-on-ipfs.org/wiki","text":"1.994","font":{"color":"#EEEEEE"},"showarrow":false},{"xref":"x1","yref":"y1","x":"us-east-2","y":"en.wikipedia-on-ipfs.org/wiki","text":"3.335","font":{"color":"#EEEEEE"},"showarrow":false},{"xref":"x1","yref":"y1","x":"us-west-1","y":"en.wikipedia-on-ipfs.org/wiki","text":"2.497","font":{"color":"#EEEEEE"},"showarrow":false},{"xref":"x1","yref":"y1","x":"ap-southeast-2","y":"ipfs.tech","text":"1.428","font":{"color":""},"showarrow":false},{"xref":"x1","yref":"y1","x":"eu-central-1","y":"ipfs.tech","text":"0.310","font":{"color":""},"showarrow":false},{"xref":"x1","yref":"y1","x":"us-east-2","y":"ipfs.tech","text":"0.328","font":{"color":""},"showarrow":false},{"xref":"x1","yref":"y1","x":"us-west-1","y":"ipfs.tech","text":"0.283","font":{"color":""},"showarrow":false},{"xref":"x1","yref":"y1","x":"ap-southeast-2","y":"ipld.io","text":"1.159","font":{"color":""},"showarrow":false},{"xref":"x1","yref":"y1","x":"eu-central-1","y":"ipld.io","text":"0.234","font":{"color":""},"showarrow":false},{"xref":"x1","yref":"y1","x":"us-east-2","y":"ipld.io","text":"0.268","font":{"color":""},"showarrow":false},{"xref":"x1","yref":"y1","x":"us-west-1","y":"ipld.io","text":"0.216","font":{"color":""},"showarrow":false},{"xref":"x1","yref":"y1","x":"ap-southeast-2","y":"probelab.io","text":"1.362","font":{"color":""},"showarrow":false},{"xref":"x1","yref":"y1","x":"eu-central-1","y":"probelab.io","text":"0.240","font":{"color":""},"showarrow":false},{"xref":"x1","yref":"y1","x":"us-east-2","y":"probelab.io","text":"0.308","font":{"color":""},"showarrow":false},{"xref":"x1","yref":"y1","x":"us-west-1","y":"probelab.io","text":"0.227","font":{"color":""},"showarrow":false},{"xref":"x1","yref":"y1","x":"ap-southeast-2","y":"specs.ipfs.tech","text":"0.971","font":{"color":""},"showarrow":false},{"xref":"x1","yref":"y1","x":"eu-central-1","y":"specs.ipfs.tech","text":"0.176","font":{"color":""},"showarrow":false},{"xref":"x1","yref":"y1","x":"us-east-2","y":"specs.ipfs.tech","text":"0.200","font":{"color":""},"showarrow":false},{"xref":"x1","yref":"y1","x":"us-west-1","y":"specs.ipfs.tech","text":"0.147","font":{"color":""},"showarrow":false},{"xref":"x1","yref":"y1","x":"ap-southeast-2","y":"web3.storage","text":"1.348","font":{"color":""},"showarrow":false},{"xref":"x1","yref":"y1","x":"eu-central-1","y":"web3.storage","text":"0.279","font":{"color":""},"showarrow":false},{"xref":"x1","yref":"y1","x":"us-east-2","y":"web3.storage","text":"0.303","font":{"color":""},"showarrow":false},{"xref":"x1","yref":"y1","x":"us-west-1","y":"web3.storage","text":"0.240","font":{"color":""},"showarrow":false}],"dragmode":false,"margin":{"b":30},"title":{"font":{"size":10},"text":"Data: 9 Aug 2025 - 16 Aug 2025 (p50, fcp, KUBO). Source: Tiros.","x":0.99,"xanchor":"right","y":0.01,"yanchor":"bottom"},"xaxis":{"automargin":true,"side":"top","title":{"text":"AWS Region"}},"yaxis":{"automargin":true,"title":{"text":"Website"}}},"params":null,"dynamicLayout":null,"config":null}
