{"data":[{"type":"heatmap","colorbar":{"title":{"side":"right","text":"← KUBO faster | HTTP faster →"}},"colorscale":"Viridis","name":"name","reversescale":true,"x":["af-south-1","ap-south-1","ap-southeast-2","eu-central-1","sa-east-1","us-east-2","us-west-1"],"y":[30,40,50,60,70,80,90],"yaxis":"","z":[[22.66521739130435,25.521505376344088,38.52020202020202,4.055793991416309,31.971014492753625,14.628099173553718,9.380952380952381],[22.2563025210084,25.18274111675127,37.853658536585364,4.4896265560165975,30.053333333333335,14.848605577689241,14.925],[22.065306122448977,24.400900900900897,37.490566037735846,4.8999999999999995,28.117886178861788,14.896551724137929,15.219999999999999],[21.72265625,22.861111111111107,37.39819004524887,5.346153846153847,26.511194029850746,14.806451612903226,15.795366795366796],[21.425992779783396,21.863309352517987,40.064935064935064,5.684587813620071,25.505119453924912,14.044585987261147,16.67279411764706],[23.05960264900662,19.44848484848485,38.42687747035573,5.818471337579618,25.145110410094638,13.618784530386739,17.713333333333335],[21.30150753768844,9.496010638297872,33.096385542168676,8.420054200542005,24.856368563685635,12.658695652173915,17.420454545454543]]}],"layout":{"annotations":[{"xref":"x1","yref":"y1","x":"af-south-1","y":30,"text":"22.665","font":{"color":"#EEEEEE"},"showarrow":false},{"xref":"x1","yref":"y1","x":"ap-south-1","y":30,"text":"25.522","font":{"color":"#EEEEEE"},"showarrow":false},{"xref":"x1","yref":"y1","x":"ap-southeast-2","y":30,"text":"38.520","font":{"color":"#EEEEEE"},"showarrow":false},{"xref":"x1","yref":"y1","x":"eu-central-1","y":30,"text":"4.056","font":{"color":""},"showarrow":false},{"xref":"x1","yref":"y1","x":"sa-east-1","y":30,"text":"31.971","font":{"color":"#EEEEEE"},"showarrow":false},{"xref":"x1","yref":"y1","x":"us-east-2","y":30,"text":"14.628","font":{"color":"#EEEEEE"},"showarrow":false},{"xref":"x1","yref":"y1","x":"us-west-1","y":30,"text":"9.381","font":{"color":""},"showarrow":false},{"xref":"x1","yref":"y1","x":"af-south-1","y":40,"text":"22.256","font":{"color":"#EEEEEE"},"showarrow":false},{"xref":"x1","yref":"y1","x":"ap-south-1","y":40,"text":"25.183","font":{"color":"#EEEEEE"},"showarrow":false},{"xref":"x1","yref":"y1","x":"ap-southeast-2","y":40,"text":"37.854","font":{"color":"#EEEEEE"},"showarrow":false},{"xref":"x1","yref":"y1","x":"eu-central-1","y":40,"text":"4.490","font":{"color":""},"showarrow":false},{"xref":"x1","yref":"y1","x":"sa-east-1","y":40,"text":"30.053","font":{"color":"#EEEEEE"},"showarrow":false},{"xref":"x1","yref":"y1","x":"us-east-2","y":40,"text":"14.849","font":{"color":"#EEEEEE"},"showarrow":false},{"xref":"x1","yref":"y1","x":"us-west-1","y":40,"text":"14.925","font":{"color":"#EEEEEE"},"showarrow":false},{"xref":"x1","yref":"y1","x":"af-south-1","y":50,"text":"22.065","font":{"color":"#EEEEEE"},"showarrow":false},{"xref":"x1","yref":"y1","x":"ap-south-1","y":50,"text":"24.401","font":{"color":"#EEEEEE"},"showarrow":false},{"xref":"x1","yref":"y1","x":"ap-southeast-2","y":50,"text":"37.491","font":{"color":"#EEEEEE"},"showarrow":false},{"xref":"x1","yref":"y1","x":"eu-central-1","y":50,"text":"4.900","font":{"color":""},"showarrow":false},{"xref":"x1","yref":"y1","x":"sa-east-1","y":50,"text":"28.118","font":{"color":"#EEEEEE"},"showarrow":false},{"xref":"x1","yref":"y1","x":"us-east-2","y":50,"text":"14.897","font":{"color":"#EEEEEE"},"showarrow":false},{"xref":"x1","yref":"y1","x":"us-west-1","y":50,"text":"15.220","font":{"color":"#EEEEEE"},"showarrow":false},{"xref":"x1","yref":"y1","x":"af-south-1","y":60,"text":"21.723","font":{"color":"#EEEEEE"},"showarrow":false},{"xref":"x1","yref":"y1","x":"ap-south-1","y":60,"text":"22.861","font":{"color":"#EEEEEE"},"showarrow":false},{"xref":"x1","yref":"y1","x":"ap-southeast-2","y":60,"text":"37.398","font":{"color":"#EEEEEE"},"showarrow":false},{"xref":"x1","yref":"y1","x":"eu-central-1","y":60,"text":"5.346","font":{"color":""},"showarrow":false},{"xref":"x1","yref":"y1","x":"sa-east-1","y":60,"text":"26.511","font":{"color":"#EEEEEE"},"showarrow":false},{"xref":"x1","yref":"y1","x":"us-east-2","y":60,"text":"14.806","font":{"color":"#EEEEEE"},"showarrow":false},{"xref":"x1","yref":"y1","x":"us-west-1","y":60,"text":"15.795","font":{"color":"#EEEEEE"},"showarrow":false},{"xref":"x1","yref":"y1","x":"af-south-1","y":70,"text":"21.426","font":{"color":"#EEEEEE"},"showarrow":false},{"xref":"x1","yref":"y1","x":"ap-south-1","y":70,"text":"21.863","font":{"color":"#EEEEEE"},"showarrow":false},{"xref":"x1","yref":"y1","x":"ap-southeast-2","y":70,"text":"40.065","font":{"color":"#EEEEEE"},"showarrow":false},{"xref":"x1","yref":"y1","x":"eu-central-1","y":70,"text":"5.685","font":{"color":""},"showarrow":false},{"xref":"x1","yref":"y1","x":"sa-east-1","y":70,"text":"25.505","font":{"color":"#EEEEEE"},"showarrow":false},{"xref":"x1","yref":"y1","x":"us-east-2","y":70,"text":"14.045","font":{"color":"#EEEEEE"},"showarrow":false},{"xref":"x1","yref":"y1","x":"us-west-1","y":70,"text":"16.673","font":{"color":"#EEEEEE"},"showarrow":false},{"xref":"x1","yref":"y1","x":"af-south-1","y":80,"text":"23.060","font":{"color":"#EEEEEE"},"showarrow":false},{"xref":"x1","yref":"y1","x":"ap-south-1","y":80,"text":"19.448","font":{"color":"#EEEEEE"},"showarrow":false},{"xref":"x1","yref":"y1","x":"ap-southeast-2","y":80,"text":"38.427","font":{"color":"#EEEEEE"},"showarrow":false},{"xref":"x1","yref":"y1","x":"eu-central-1","y":80,"text":"5.818","font":{"color":""},"showarrow":false},{"xref":"x1","yref":"y1","x":"sa-east-1","y":80,"text":"25.145","font":{"color":"#EEEEEE"},"showarrow":false},{"xref":"x1","yref":"y1","x":"us-east-2","y":80,"text":"13.619","font":{"color":"#EEEEEE"},"showarrow":false},{"xref":"x1","yref":"y1","x":"us-west-1","y":80,"text":"17.713","font":{"color":"#EEEEEE"},"showarrow":false},{"xref":"x1","yref":"y1","x":"af-south-1","y":90,"text":"21.302","font":{"color":"#EEEEEE"},"showarrow":false},{"xref":"x1","yref":"y1","x":"ap-south-1","y":90,"text":"9.496","font":{"color":""},"showarrow":false},{"xref":"x1","yref":"y1","x":"ap-southeast-2","y":90,"text":"33.096","font":{"color":"#EEEEEE"},"showarrow":false},{"xref":"x1","yref":"y1","x":"eu-central-1","y":90,"text":"8.420","font":{"color":""},"showarrow":false},{"xref":"x1","yref":"y1","x":"sa-east-1","y":90,"text":"24.856","font":{"color":"#EEEEEE"},"showarrow":false},{"xref":"x1","yref":"y1","x":"us-east-2","y":90,"text":"12.659","font":{"color":"#EEEEEE"},"showarrow":false},{"xref":"x1","yref":"y1","x":"us-west-1","y":90,"text":"17.420","font":{"color":"#EEEEEE"},"showarrow":false}],"dragmode":false,"margin":{"b":30},"title":{"font":{"size":10},"text":"Data: 6 Jan 2024 - 13 Jan 2024 (ttfb, n0.computer). Source: Tiros.","x":1,"xanchor":"right","y":0.01,"yanchor":"bottom"},"xaxis":{"automargin":true,"side":"top","title":{"text":"AWS Region"}},"yaxis":{"automargin":true,"title":{"text":"Percentile"}}},"params":null,"dynamicLayout":null,"config":null}
