{"data":[{"type":"heatmap","colorbar":{"title":{"side":"right","text":"← KUBO faster | HTTP faster →"}},"colorscale":"Viridis","name":"name","reversescale":true,"x":["af-south-1","ap-south-1","ap-southeast-2","eu-central-1","sa-east-1","us-east-2","us-west-1"],"y":[30,40,50,60,70,80,90],"yaxis":"","z":[[5.463804847140821,4.325375293904866,2.543314711359404,34.049429657794676,3.4351335986355886,5.0043134435657795,3.843794920939147],[6.413776796973519,5.406059519541055,2.898367678558239,44.82830188679246,4.0947797531423396,7.023095238095238,5.00771410579345],[7.50929542259022,6.370910384068279,3.2758044599404372,52.51111111111111,4.7008681925808995,8.381457891012031,5.763012011087158],[8.795732178753672,7.617077003666842,3.7147892288171436,65.72413793103448,5.345644364616075,10.255716285580961,7.557451996342579],[10.574261992619927,9.103030303030302,4.503365586874211,80.09548611111111,6.584149599287622,12.266013220879874,9.373181340932954],[12.920577617328522,10.216400580551525,5.542770836193877,102.434439178515,8.06957358127605,15.212248507627681,12.303833062009769],[13.508077852690498,11.758062492157107,6.421318196152633,130.71126760563382,9.29077809798271,21.28141962421712,15.013918477488994]]}],"layout":{"annotations":[{"xref":"x1","yref":"y1","x":"af-south-1","y":30,"text":"5.464","font":{"color":""},"showarrow":false},{"xref":"x1","yref":"y1","x":"ap-south-1","y":30,"text":"4.325","font":{"color":""},"showarrow":false},{"xref":"x1","yref":"y1","x":"ap-southeast-2","y":30,"text":"2.543","font":{"color":""},"showarrow":false},{"xref":"x1","yref":"y1","x":"eu-central-1","y":30,"text":"34.049","font":{"color":""},"showarrow":false},{"xref":"x1","yref":"y1","x":"sa-east-1","y":30,"text":"3.435","font":{"color":""},"showarrow":false},{"xref":"x1","yref":"y1","x":"us-east-2","y":30,"text":"5.004","font":{"color":""},"showarrow":false},{"xref":"x1","yref":"y1","x":"us-west-1","y":30,"text":"3.844","font":{"color":""},"showarrow":false},{"xref":"x1","yref":"y1","x":"af-south-1","y":40,"text":"6.414","font":{"color":""},"showarrow":false},{"xref":"x1","yref":"y1","x":"ap-south-1","y":40,"text":"5.406","font":{"color":""},"showarrow":false},{"xref":"x1","yref":"y1","x":"ap-southeast-2","y":40,"text":"2.898","font":{"color":""},"showarrow":false},{"xref":"x1","yref":"y1","x":"eu-central-1","y":40,"text":"44.828","font":{"color":"#EEEEEE"},"showarrow":false},{"xref":"x1","yref":"y1","x":"sa-east-1","y":40,"text":"4.095","font":{"color":""},"showarrow":false},{"xref":"x1","yref":"y1","x":"us-east-2","y":40,"text":"7.023","font":{"color":""},"showarrow":false},{"xref":"x1","yref":"y1","x":"us-west-1","y":40,"text":"5.008","font":{"color":""},"showarrow":false},{"xref":"x1","yref":"y1","x":"af-south-1","y":50,"text":"7.509","font":{"color":""},"showarrow":false},{"xref":"x1","yref":"y1","x":"ap-south-1","y":50,"text":"6.371","font":{"color":""},"showarrow":false},{"xref":"x1","yref":"y1","x":"ap-southeast-2","y":50,"text":"3.276","font":{"color":""},"showarrow":false},{"xref":"x1","yref":"y1","x":"eu-central-1","y":50,"text":"52.511","font":{"color":"#EEEEEE"},"showarrow":false},{"xref":"x1","yref":"y1","x":"sa-east-1","y":50,"text":"4.701","font":{"color":""},"showarrow":false},{"xref":"x1","yref":"y1","x":"us-east-2","y":50,"text":"8.381","font":{"color":""},"showarrow":false},{"xref":"x1","yref":"y1","x":"us-west-1","y":50,"text":"5.763","font":{"color":""},"showarrow":false},{"xref":"x1","yref":"y1","x":"af-south-1","y":60,"text":"8.796","font":{"color":""},"showarrow":false},{"xref":"x1","yref":"y1","x":"ap-south-1","y":60,"text":"7.617","font":{"color":""},"showarrow":false},{"xref":"x1","yref":"y1","x":"ap-southeast-2","y":60,"text":"3.715","font":{"color":""},"showarrow":false},{"xref":"x1","yref":"y1","x":"eu-central-1","y":60,"text":"65.724","font":{"color":"#EEEEEE"},"showarrow":false},{"xref":"x1","yref":"y1","x":"sa-east-1","y":60,"text":"5.346","font":{"color":""},"showarrow":false},{"xref":"x1","yref":"y1","x":"us-east-2","y":60,"text":"10.256","font":{"color":""},"showarrow":false},{"xref":"x1","yref":"y1","x":"us-west-1","y":60,"text":"7.557","font":{"color":""},"showarrow":false},{"xref":"x1","yref":"y1","x":"af-south-1","y":70,"text":"10.574","font":{"color":""},"showarrow":false},{"xref":"x1","yref":"y1","x":"ap-south-1","y":70,"text":"9.103","font":{"color":""},"showarrow":false},{"xref":"x1","yref":"y1","x":"ap-southeast-2","y":70,"text":"4.503","font":{"color":""},"showarrow":false},{"xref":"x1","yref":"y1","x":"eu-central-1","y":70,"text":"80.095","font":{"color":"#EEEEEE"},"showarrow":false},{"xref":"x1","yref":"y1","x":"sa-east-1","y":70,"text":"6.584","font":{"color":""},"showarrow":false},{"xref":"x1","yref":"y1","x":"us-east-2","y":70,"text":"12.266","font":{"color":""},"showarrow":false},{"xref":"x1","yref":"y1","x":"us-west-1","y":70,"text":"9.373","font":{"color":""},"showarrow":false},{"xref":"x1","yref":"y1","x":"af-south-1","y":80,"text":"12.921","font":{"color":""},"showarrow":false},{"xref":"x1","yref":"y1","x":"ap-south-1","y":80,"text":"10.216","font":{"color":""},"showarrow":false},{"xref":"x1","yref":"y1","x":"ap-southeast-2","y":80,"text":"5.543","font":{"color":""},"showarrow":false},{"xref":"x1","yref":"y1","x":"eu-central-1","y":80,"text":"102.434","font":{"color":"#EEEEEE"},"showarrow":false},{"xref":"x1","yref":"y1","x":"sa-east-1","y":80,"text":"8.070","font":{"color":""},"showarrow":false},{"xref":"x1","yref":"y1","x":"us-east-2","y":80,"text":"15.212","font":{"color":""},"showarrow":false},{"xref":"x1","yref":"y1","x":"us-west-1","y":80,"text":"12.304","font":{"color":""},"showarrow":false},{"xref":"x1","yref":"y1","x":"af-south-1","y":90,"text":"13.508","font":{"color":""},"showarrow":false},{"xref":"x1","yref":"y1","x":"ap-south-1","y":90,"text":"11.758","font":{"color":""},"showarrow":false},{"xref":"x1","yref":"y1","x":"ap-southeast-2","y":90,"text":"6.421","font":{"color":""},"showarrow":false},{"xref":"x1","yref":"y1","x":"eu-central-1","y":90,"text":"130.711","font":{"color":"#EEEEEE"},"showarrow":false},{"xref":"x1","yref":"y1","x":"sa-east-1","y":90,"text":"9.291","font":{"color":""},"showarrow":false},{"xref":"x1","yref":"y1","x":"us-east-2","y":90,"text":"21.281","font":{"color":""},"showarrow":false},{"xref":"x1","yref":"y1","x":"us-west-1","y":90,"text":"15.014","font":{"color":""},"showarrow":false}],"dragmode":false,"margin":{"b":30},"title":{"font":{"size":10},"text":"Data: 28 Sep 2024 - 5 Oct 2024 (ttfb, en.wikipedia-on-ipfs.org/wiki). Source: Tiros.","x":1,"xanchor":"right","y":0.01,"yanchor":"bottom"},"xaxis":{"automargin":true,"side":"top","title":{"text":"AWS Region"}},"yaxis":{"automargin":true,"title":{"text":"Percentile"}}},"params":null,"dynamicLayout":null,"config":null}
