{"data":[{"type":"heatmap","colorbar":{"title":{"side":"right","text":"← KUBO faster | HTTP faster →"}},"colorscale":"Viridis","name":"name","reversescale":true,"x":["af-south-1","ap-south-1","ap-southeast-2","eu-central-1","sa-east-1","us-east-2","us-west-1"],"y":[30,40,50,60,70,80,90],"yaxis":"","z":[[1.5842732327243845,1.702160760587727,1.1985185185185188,1.9689922480620154,1.1321105465361259,2.56021650879567,0.21964000911369333],[1.5406304222093694,1.6665590182464074,1.2561676241973638,2.072753209700428,1.1537046123650638,1.1918505942275044,0.2435813034891376],[1.4709867075664622,1.6971183323114654,1.3349676844216625,2.1406649616368285,1.2299128751210067,0.6982404692082111,0.30851519041506204],[1.5503397158739962,1.7397517321016167,1.4972393992932864,2.2892561983471076,1.2860164512338426,0.7353837628151844,0.39239176124422026],[1.5609248301555996,1.7748101952277655,1.6363338072842613,2.513274336283186,1.3584739221523872,0.8708732694355698,0.5180348258706468],[1.6839320240154676,1.9272103658536583,1.6845975622040896,2.7707267144319347,1.4720050707796324,0.9716618635926993,0.7602434077079108],[1.7507771560529357,2.020828667413214,1.9062674874090653,3.4799999999999995,1.6650871872630781,1.2642825011246066,1.2395339652448658]]}],"layout":{"annotations":[{"xref":"x1","yref":"y1","x":"af-south-1","y":30,"text":"1.584","font":{"color":"#EEEEEE"},"showarrow":false},{"xref":"x1","yref":"y1","x":"ap-south-1","y":30,"text":"1.702","font":{"color":"#EEEEEE"},"showarrow":false},{"xref":"x1","yref":"y1","x":"ap-southeast-2","y":30,"text":"1.199","font":{"color":"#EEEEEE"},"showarrow":false},{"xref":"x1","yref":"y1","x":"eu-central-1","y":30,"text":"1.969","font":{"color":"#EEEEEE"},"showarrow":false},{"xref":"x1","yref":"y1","x":"sa-east-1","y":30,"text":"1.132","font":{"color":"#EEEEEE"},"showarrow":false},{"xref":"x1","yref":"y1","x":"us-east-2","y":30,"text":"2.560","font":{"color":"#EEEEEE"},"showarrow":false},{"xref":"x1","yref":"y1","x":"us-west-1","y":30,"text":"0.220","font":{"color":""},"showarrow":false},{"xref":"x1","yref":"y1","x":"af-south-1","y":40,"text":"1.541","font":{"color":"#EEEEEE"},"showarrow":false},{"xref":"x1","yref":"y1","x":"ap-south-1","y":40,"text":"1.667","font":{"color":"#EEEEEE"},"showarrow":false},{"xref":"x1","yref":"y1","x":"ap-southeast-2","y":40,"text":"1.256","font":{"color":"#EEEEEE"},"showarrow":false},{"xref":"x1","yref":"y1","x":"eu-central-1","y":40,"text":"2.073","font":{"color":"#EEEEEE"},"showarrow":false},{"xref":"x1","yref":"y1","x":"sa-east-1","y":40,"text":"1.154","font":{"color":"#EEEEEE"},"showarrow":false},{"xref":"x1","yref":"y1","x":"us-east-2","y":40,"text":"1.192","font":{"color":"#EEEEEE"},"showarrow":false},{"xref":"x1","yref":"y1","x":"us-west-1","y":40,"text":"0.244","font":{"color":""},"showarrow":false},{"xref":"x1","yref":"y1","x":"af-south-1","y":50,"text":"1.471","font":{"color":"#EEEEEE"},"showarrow":false},{"xref":"x1","yref":"y1","x":"ap-south-1","y":50,"text":"1.697","font":{"color":"#EEEEEE"},"showarrow":false},{"xref":"x1","yref":"y1","x":"ap-southeast-2","y":50,"text":"1.335","font":{"color":"#EEEEEE"},"showarrow":false},{"xref":"x1","yref":"y1","x":"eu-central-1","y":50,"text":"2.141","font":{"color":"#EEEEEE"},"showarrow":false},{"xref":"x1","yref":"y1","x":"sa-east-1","y":50,"text":"1.230","font":{"color":"#EEEEEE"},"showarrow":false},{"xref":"x1","yref":"y1","x":"us-east-2","y":50,"text":"0.698","font":{"color":""},"showarrow":false},{"xref":"x1","yref":"y1","x":"us-west-1","y":50,"text":"0.309","font":{"color":""},"showarrow":false},{"xref":"x1","yref":"y1","x":"af-south-1","y":60,"text":"1.550","font":{"color":"#EEEEEE"},"showarrow":false},{"xref":"x1","yref":"y1","x":"ap-south-1","y":60,"text":"1.740","font":{"color":"#EEEEEE"},"showarrow":false},{"xref":"x1","yref":"y1","x":"ap-southeast-2","y":60,"text":"1.497","font":{"color":"#EEEEEE"},"showarrow":false},{"xref":"x1","yref":"y1","x":"eu-central-1","y":60,"text":"2.289","font":{"color":"#EEEEEE"},"showarrow":false},{"xref":"x1","yref":"y1","x":"sa-east-1","y":60,"text":"1.286","font":{"color":"#EEEEEE"},"showarrow":false},{"xref":"x1","yref":"y1","x":"us-east-2","y":60,"text":"0.735","font":{"color":""},"showarrow":false},{"xref":"x1","yref":"y1","x":"us-west-1","y":60,"text":"0.392","font":{"color":""},"showarrow":false},{"xref":"x1","yref":"y1","x":"af-south-1","y":70,"text":"1.561","font":{"color":"#EEEEEE"},"showarrow":false},{"xref":"x1","yref":"y1","x":"ap-south-1","y":70,"text":"1.775","font":{"color":"#EEEEEE"},"showarrow":false},{"xref":"x1","yref":"y1","x":"ap-southeast-2","y":70,"text":"1.636","font":{"color":"#EEEEEE"},"showarrow":false},{"xref":"x1","yref":"y1","x":"eu-central-1","y":70,"text":"2.513","font":{"color":"#EEEEEE"},"showarrow":false},{"xref":"x1","yref":"y1","x":"sa-east-1","y":70,"text":"1.358","font":{"color":"#EEEEEE"},"showarrow":false},{"xref":"x1","yref":"y1","x":"us-east-2","y":70,"text":"0.871","font":{"color":""},"showarrow":false},{"xref":"x1","yref":"y1","x":"us-west-1","y":70,"text":"0.518","font":{"color":""},"showarrow":false},{"xref":"x1","yref":"y1","x":"af-south-1","y":80,"text":"1.684","font":{"color":"#EEEEEE"},"showarrow":false},{"xref":"x1","yref":"y1","x":"ap-south-1","y":80,"text":"1.927","font":{"color":"#EEEEEE"},"showarrow":false},{"xref":"x1","yref":"y1","x":"ap-southeast-2","y":80,"text":"1.685","font":{"color":"#EEEEEE"},"showarrow":false},{"xref":"x1","yref":"y1","x":"eu-central-1","y":80,"text":"2.771","font":{"color":"#EEEEEE"},"showarrow":false},{"xref":"x1","yref":"y1","x":"sa-east-1","y":80,"text":"1.472","font":{"color":"#EEEEEE"},"showarrow":false},{"xref":"x1","yref":"y1","x":"us-east-2","y":80,"text":"0.972","font":{"color":"#EEEEEE"},"showarrow":false},{"xref":"x1","yref":"y1","x":"us-west-1","y":80,"text":"0.760","font":{"color":""},"showarrow":false},{"xref":"x1","yref":"y1","x":"af-south-1","y":90,"text":"1.751","font":{"color":"#EEEEEE"},"showarrow":false},{"xref":"x1","yref":"y1","x":"ap-south-1","y":90,"text":"2.021","font":{"color":"#EEEEEE"},"showarrow":false},{"xref":"x1","yref":"y1","x":"ap-southeast-2","y":90,"text":"1.906","font":{"color":"#EEEEEE"},"showarrow":false},{"xref":"x1","yref":"y1","x":"eu-central-1","y":90,"text":"3.480","font":{"color":"#EEEEEE"},"showarrow":false},{"xref":"x1","yref":"y1","x":"sa-east-1","y":90,"text":"1.665","font":{"color":"#EEEEEE"},"showarrow":false},{"xref":"x1","yref":"y1","x":"us-east-2","y":90,"text":"1.264","font":{"color":"#EEEEEE"},"showarrow":false},{"xref":"x1","yref":"y1","x":"us-west-1","y":90,"text":"1.240","font":{"color":"#EEEEEE"},"showarrow":false}],"dragmode":false,"margin":{"b":30},"title":{"font":{"size":10},"text":"Data: 17 Nov 2023 - 24 Nov 2023 (ttfb, green.filecoin.io). Source: Tiros.","x":1,"xanchor":"right","y":0.01,"yanchor":"bottom"},"xaxis":{"automargin":true,"side":"top","title":{"text":"AWS Region"}},"yaxis":{"automargin":true,"title":{"text":"Percentile"}}},"params":null,"dynamicLayout":null,"config":null}
